aiha-0.0.1.dist-info/METADATA
aiha-0.0.1.dist-info/WHEEL
aiha-0.0.1.dist-info/license_files/LICENSE
aiha/__init__.py
aiha/aiha.cpython-310-darwin.so
aiha-0.0.1.dist-info/RECORD
