Metadata-Version: 2.1
Name: aiha
Version: 0.0.1
Classifier: Programming Language :: Rust
Classifier: Programming Language :: Python :: Implementation :: CPython
Classifier: Programming Language :: Python :: Implementation :: PyPy
License-File: LICENSE
Summary: 🦉 AIHA helps you to find the minimal requirements for any model on the 🤗 Hub.
Keywords: ai,hardware,advisor,huggingface,NLP
Home-Page: https://github.com/chainyo/aiha
Author: Thomas Chaigneau <t.chaigneau.tc@gmail.com>
Author-email: Thomas Chaigneau <t.chaigneau.tc@gmail.com>
License: Apache-2.0
Requires-Python: >=3.8
Project-URL: Source Code, https://github.com/chainyo/aiha
